pytest_unstable.py
pytest_unstable-0.1.0.dist-info/DESCRIPTION.rst
pytest_unstable-0.1.0.dist-info/METADATA
pytest_unstable-0.1.0.dist-info/RECORD
pytest_unstable-0.1.0.dist-info/WHEEL
pytest_unstable-0.1.0.dist-info/entry_points.txt
pytest_unstable-0.1.0.dist-info/metadata.json
pytest_unstable-0.1.0.dist-info/top_level.txt
