Metadata-Version: 2.0
Name: pytest-unstable
Version: 0.1.0
Summary: Set a test as unstable to return 0 even if it failed
Home-page: https://github.com/Salamandar/pytest-unstable
Author: Salamandar
Author-email: felix@piedallu.me
Maintainer: Salamandar
Maintainer-email: felix@piedallu.me
License: MIT
Platform: UNKNOWN
Classifier: Development Status :: 4 - Beta
Classifier: Framework :: Pytest
Classifier: Intended Audience :: Developers
Classifier: Topic :: Software Development :: Testing
Classifier: Programming Language :: Python
Classifier: Programming Language :: Python :: 3
Classifier: Programming Language :: Python :: 3.5
Classifier: Programming Language :: Python :: 3.6
Classifier: Programming Language :: Python :: 3.7
Classifier: Programming Language :: Python :: 3.8
Classifier: Programming Language :: Python :: 3 :: Only
Classifier: Programming Language :: Python :: Implementation :: CPython
Classifier: Programming Language :: Python :: Implementation :: PyPy
Classifier: Operating System :: OS Independent
Classifier: License :: OSI Approved :: MIT License
Requires-Python: >=3.5
Requires-Dist: pytest (>=3.5.0)
